capymoa/__about__.py
capymoa/__init__.py
capymoa/_pickle.py
capymoa/_prepare_jpype.py
capymoa/_utils.py
capymoa/env.py
capymoa/exception.py
capymoa/instance.py
capymoa/misc.py
capymoa/splitcriteria.py
capymoa/type_alias.py
capymoa/ann/__init__.py
capymoa/ann/_lenet.py
capymoa/ann/_perceptron.py
capymoa/ann/_resnet.py
capymoa/ann/util.py
capymoa/anomaly/__init__.py
capymoa/anomaly/_adaptive_isolation_forest.py
capymoa/anomaly/_autoencoder.py
capymoa/anomaly/_half_space_trees.py
capymoa/anomaly/_online_isolation_forest.py
capymoa/anomaly/_robust_random_cut_forest.py
capymoa/anomaly/_stream_rhf.py
capymoa/anomaly/_streaming_isolation_forest.py
capymoa/automl/__init__.py
capymoa/automl/_autoclass.py
capymoa/automl/_bandit_classifier.py
capymoa/automl/_successive_halving_classifier.py
capymoa/automl/_utils.py
capymoa/base/__init__.py
capymoa/base/_base.py
capymoa/base/_batch.py
capymoa/base/_classifier.py
capymoa/base/_regressor.py
capymoa/base/_ssl.py
capymoa/classifier/__init__.py
capymoa/classifier/_adaptive_random_forest.py
capymoa/classifier/_csmote.py
capymoa/classifier/_dynamic_weighted_majority.py
capymoa/classifier/_efdt.py
capymoa/classifier/_finetune.py
capymoa/classifier/_hoeffding_adaptive_tree.py
capymoa/classifier/_hoeffding_tree.py
capymoa/classifier/_knn.py
capymoa/classifier/_leveraging_bagging.py
capymoa/classifier/_majority_class.py
capymoa/classifier/_naive_bayes.py
capymoa/classifier/_no_change.py
capymoa/classifier/_online_adwin_bagging.py
capymoa/classifier/_online_bagging.py
capymoa/classifier/_online_smooth_boost.py
capymoa/classifier/_oza_boost.py
capymoa/classifier/_passive_aggressive_classifier.py
capymoa/classifier/_samknn.py
capymoa/classifier/_sgbt.py
capymoa/classifier/_sgd_classifier.py
capymoa/classifier/_shrubs_classifier.py
capymoa/classifier/_shrubs_ensemble.py
capymoa/classifier/_srp.py
capymoa/classifier/_weightedknn.py
capymoa/clusterers/__init__.py
capymoa/clusterers/_clustream.py
capymoa/clusterers/_clustream_with_kmeans.py
capymoa-0.12.0.dist-info/METADATA
capymoa-0.12.0.dist-info/WHEEL
capymoa-0.12.0.dist-info/licenses/LICENSE
capymoa-0.12.0.dist-info/RECORD
