Metadata-Version: 2.4
Name: capymoa
Version: 0.12.0
Summary: Python wrapper for MOA to allow efficient use of existing algorithms with a more modern API.
Project-URL: Documentation, https://capymoa.org
Project-URL: Source, https://github.com/adaptive-machine-learning/CapyMOA
Author: Nuwan Gunasekara, Marco Heyden, Yibin Sun, Guilherme Weigert Cassales
Author-email: Heitor Murilo Gomes <hmugomes@gmail.com>, Anton Lee <anton.lee@vuw.ac.nz>
License-Expression: BSD-3-Clause
License-File: LICENSE
Keywords: Big Data,Concept Drift,Concept Evolution,Concept Shift,Data Mining,Data Science,Data Stream,Data Stream Mining,Incremental Learning,MOA,Machine Learning,Online Learning,Stream Learning
Requires-Python: >=3.9
Requires-Dist: deprecated~=1.3
Requires-Dist: jpype1~=1.6
Requires-Dist: matplotlib~=3.10
Requires-Dist: numpy~=2.2
Requires-Dist: pandas~=2.2
Requires-Dist: scikit-learn~=1.7
Requires-Dist: seaborn~=0.13
Requires-Dist: tqdm~=4.67
Provides-Extra: dev
Requires-Dist: commitizen~=3.24; extra == 'dev'
Requires-Dist: invoke~=2.2; extra == 'dev'
Requires-Dist: jupyter~=1.1; extra == 'dev'
Requires-Dist: nbmake~=1.5; extra == 'dev'
Requires-Dist: pytest-subtests~=0.15; extra == 'dev'
Requires-Dist: pytest-xdist~=3.8; extra == 'dev'
Requires-Dist: pytest~=9.0; extra == 'dev'
Requires-Dist: ruff~=0.14; extra == 'dev'
Requires-Dist: stubgenj~=0.2; extra == 'dev'
Requires-Dist: wget~=3.2; extra == 'dev'
Provides-Extra: doc
Requires-Dist: myst-parser; extra == 'doc'
Requires-Dist: nbsphinx; extra == 'doc'
Requires-Dist: pydata-sphinx-theme; extra == 'doc'
Requires-Dist: sphinx-autobuild; extra == 'doc'
Requires-Dist: sphinx-design; extra == 'doc'
Requires-Dist: sphinx==8.1.3; extra == 'doc'
Requires-Dist: sphinxcontrib-programoutput; extra == 'doc'
